cmlibs.zinc-4.2.1.data/purelib/cmlibs/__init__.py
cmlibs.zinc-4.2.1.data/purelib/cmlibs/zinc/__init__.py
cmlibs.zinc-4.2.1.data/purelib/cmlibs/zinc/_context.so
cmlibs.zinc-4.2.1.data/purelib/cmlibs/zinc/_differentialoperator.so
cmlibs.zinc-4.2.1.data/purelib/cmlibs/zinc/_element.so
cmlibs.zinc-4.2.1.data/purelib/cmlibs/zinc/_field.so
cmlibs.zinc-4.2.1.data/purelib/cmlibs/zinc/_fieldassignment.so
cmlibs.zinc-4.2.1.data/purelib/cmlibs/zinc/_fieldcache.so
cmlibs.zinc-4.2.1.data/purelib/cmlibs/zinc/_fieldmodule.so
cmlibs.zinc-4.2.1.data/purelib/cmlibs/zinc/_fieldparameters.so
cmlibs.zinc-4.2.1.data/purelib/cmlibs/zinc/_fieldrange.so
cmlibs.zinc-4.2.1.data/purelib/cmlibs/zinc/_fieldsmoothing.so
cmlibs.zinc-4.2.1.data/purelib/cmlibs/zinc/_font.so
cmlibs.zinc-4.2.1.data/purelib/cmlibs/zinc/_glyph.so
cmlibs.zinc-4.2.1.data/purelib/cmlibs/zinc/_graphics.so
cmlibs.zinc-4.2.1.data/purelib/cmlibs/zinc/_light.so
cmlibs.zinc-4.2.1.data/purelib/cmlibs/zinc/_logger.so
cmlibs.zinc-4.2.1.data/purelib/cmlibs/zinc/_material.so
cmlibs.zinc-4.2.1.data/purelib/cmlibs/zinc/_node.so
cmlibs.zinc-4.2.1.data/purelib/cmlibs/zinc/_optimisation.so
cmlibs.zinc-4.2.1.data/purelib/cmlibs/zinc/_region.so
cmlibs.zinc-4.2.1.data/purelib/cmlibs/zinc/_result.so
cmlibs.zinc-4.2.1.data/purelib/cmlibs/zinc/_scene.so
cmlibs.zinc-4.2.1.data/purelib/cmlibs/zinc/_scenecoordinatesystem.so
cmlibs.zinc-4.2.1.data/purelib/cmlibs/zinc/_scenefilter.so
cmlibs.zinc-4.2.1.data/purelib/cmlibs/zinc/_scenepicker.so
cmlibs.zinc-4.2.1.data/purelib/cmlibs/zinc/_sceneviewer.so
cmlibs.zinc-4.2.1.data/purelib/cmlibs/zinc/_sceneviewerinput.so
cmlibs.zinc-4.2.1.data/purelib/cmlibs/zinc/_selection.so
cmlibs.zinc-4.2.1.data/purelib/cmlibs/zinc/_shader.so
cmlibs.zinc-4.2.1.data/purelib/cmlibs/zinc/_spectrum.so
cmlibs.zinc-4.2.1.data/purelib/cmlibs/zinc/_status.so
cmlibs.zinc-4.2.1.data/purelib/cmlibs/zinc/_stream.so
cmlibs.zinc-4.2.1.data/purelib/cmlibs/zinc/_streamimage.so
cmlibs.zinc-4.2.1.data/purelib/cmlibs/zinc/_streamregion.so
cmlibs.zinc-4.2.1.dist-info/LICENSE.txt
cmlibs.zinc-4.2.1.dist-info/METADATA
cmlibs.zinc-4.2.1.dist-info/WHEEL
cmlibs.zinc-4.2.1.dist-info/top_level.txt
cmlibs.zinc-4.2.1.dist-info/RECORD
