Metadata-Version: 2.1
Name: cmlibs.zinc
Version: 4.2.1
Summary: Zinc Library: An advanced visualisation library for FE models
Home-page: https://cmlibs.org
Author: Zinc developers
Author-email: h.sorby@auckland.ac.nz
License: Mozilla Public License 2.0 (MPL 2.0)
Platform: UNKNOWN
Classifier: Development Status :: 5 - Production/Stable
Classifier: Intended Audience :: Developers
Classifier: Intended Audience :: Education
Classifier: Intended Audience :: Science/Research
Classifier: License :: OSI Approved :: Mozilla Public License 2.0 (MPL 2.0)
Classifier: Programming Language :: Python
Classifier: Operating System :: Microsoft :: Windows
Classifier: Operating System :: Unix
Classifier: Operating System :: MacOS :: MacOS X
Classifier: Topic :: Scientific/Engineering :: Medical Science Apps.
Classifier: Topic :: Scientific/Engineering :: Visualization
Classifier: Topic :: Software Development :: Libraries :: Python Modules
License-File: LICENSE.txt
